idem/conf.py
idem/scripts.py
idem/version.py
idem/acct/esm/local/init.py
idem/esm/local.py
idem/esm/null.py
idem/esm/contracts/init.py
idem/esm/upgrade/init.py
idem/esm/upgrade/v1_0_0.py
idem/esm/upgrade/v2_0_0.py
idem/esm/upgrade/contracts/init.py
idem/exec/auto.py
idem/exec/esm.py
idem/exec/init.py
idem/exec/state.py
idem/exec/test.py
idem/exec/recursive_contracts/auto_state.py
idem/exec/recursive_contracts/init.py
idem/exec/recursive_contracts/soft_fail.py
idem/group/duration.py
idem/group/init.py
idem/group/number.py
idem/group/omit_noop.py
idem/group/sort.py
idem/group/contracts/init.py
idem/idem/acct.py
idem/idem/arg_bind.py
idem/idem/cli.py
idem/idem/describe.py
idem/idem/event.py
idem/idem/ex.py
idem/idem/get.py
idem/idem/init.py
idem/idem/managed.py
idem/idem/state.py
idem/idem/tools.py
idem/idem/ccomps/arg_bind.py
idem/idem/ccomps/exclude.py
idem/idem/ccomps/extend.py
idem/idem/ccomps/invert.py
idem/idem/ccomps/low.py
idem/idem/ccomps/req_in.py
idem/idem/ccomps/treq.py
idem/idem/ccomps/verify.py
idem/idem/compiler/0001_arg_bind.py
idem/idem/compiler/0010_extend.py
idem/idem/compiler/0020_verify_high.py
idem/idem/compiler/0030_req_in.py
idem/idem/compiler/0040_exclude.py
idem/idem/compiler/0050_compile.py
idem/idem/compiler/0060_treq.py
idem/idem/compiler/0099_invert.py
idem/idem/compiler/contracts/init.py
idem/idem/contracts/cli.py
idem/idem/mod/acct.py
idem/idem/mod/aggregate.py
idem/idem/mod/init.py
idem/idem/mod/meta.py
idem/idem/mod/old_state.py
idem/idem/mod/skip_esm.py
idem/idem/mod/contracts/init.py
idem/idem/req/arg_bind.py
idem/idem/req/init.py
idem/idem/req/listen.py
idem/idem/req/onchanges.py
idem/idem/req/onchanges_any.py
idem/idem/req/onfail.py
idem/idem/req/prereq.py
idem/idem/req/recreate_if_deleted.py
idem/idem/req/recreate_on_update.py
idem/idem/req/require.py
idem/idem/req/require_any.py
idem/idem/req/sensitive.py
idem/idem/req/unique.py
idem/idem/req/watch.py
idem/idem/req/contracts/init.py
idem/idem/req/seq/0000_straight.py
idem-25.0.1.dist-info/LICENSE
idem-25.0.1.dist-info/METADATA
idem-25.0.1.dist-info/WHEEL
idem-25.0.1.dist-info/entry_points.txt
idem-25.0.1.dist-info/top_level.txt
idem-25.0.1.dist-info/RECORD
