Metadata-Version: 2.1
Name: idem
Version: 25.0.1
Summary: Transform configuration into idempotent action.
Home-page: https://docs.idemproject.io/idem/en/latest/index.html
Author: VMware, Inc.
Author-email: idemproject@vmware.com
License: Apache Software License 2.0
Project-URL: Code, https://gitlab.com/vmware/idem/idem
Project-URL: Issue tracker, https://gitlab.com/vmware/idem/idem/issues
Classifier: Environment :: Console
Classifier: Intended Audience :: Developers
Classifier: Intended Audience :: Information Technology
Classifier: Intended Audience :: System Administrators
Classifier: Operating System :: OS Independent
Classifier: Programming Language :: Python
Classifier: Programming Language :: Python :: 3.8
Classifier: Programming Language :: Python :: 3.9
Classifier: Programming Language :: Python :: 3.10
Classifier: Programming Language :: Python :: 3.11
Classifier: Development Status :: 5 - Production/Stable
Classifier: License :: OSI Approved :: Apache Software License
Requires-Python: >=3.8
License-File: LICENSE
Requires-Dist: aiofiles >=0.7.0
Requires-Dist: acct <9.0.0,>=8.5.2
Requires-Dist: dict-toolbox <5.0.0,>=4.1.0
Requires-Dist: jinja2
Requires-Dist: jmespath
Requires-Dist: pop <28.0.0,>=27.1.0
Requires-Dist: pop-evbus <8.0.0,>=6.2.0
Requires-Dist: pop-config <13.0.0,>=12.0.1
Requires-Dist: pop-loop <2.0.0,>=1.0.4
Requires-Dist: pop-serial <3.0.0,>=1.1.0
Requires-Dist: pop-tree <13.0.0,>=12.1.2
Requires-Dist: PyYaml >=6.0.1
Requires-Dist: toml
Requires-Dist: tqdm
Requires-Dist: rend <8.0.0,>=7.0.0
Requires-Dist: colorama
Requires-Dist: wheel
Requires-Dist: uvloop ; platform_system != "Windows"
Provides-Extra: full
Requires-Dist: evbus-kafka >=3.0.1 ; extra == 'full'
Requires-Dist: evbus-pika >=3.0.1 ; extra == 'full'
Provides-Extra: kafka
Requires-Dist: evbus-kafka >=3.0.1 ; extra == 'kafka'
Provides-Extra: rabbitmq
Requires-Dist: evbus-pika >=3.0.1 ; extra == 'rabbitmq'
